{"format":2,"version":"5.2.1","globals":"c3fc29d529a3af98c1a2065daa2addf6","files":{"books___init___py":{"hash":"af9d0d0de0ea3b71d198bc63f1499a7d","index":{"nums":[1,0,0,0,0,0,0],"html_filename":"books___init___py.html","relative_filename":"books\\__init__.py"}},"books_asgi_py":{"hash":"a8440463721d62e0d255cfdf8336cc8f","index":{"nums":[1,4,0,4,0,0,0],"html_filename":"books_asgi_py.html","relative_filename":"books\\asgi.py"}},"books_settings_py":{"hash":"2ea33eea947510a6878a74619097faea","index":{"nums":[1,18,0,0,0,0,0],"html_filename":"books_settings_py.html","relative_filename":"books\\settings.py"}},"books_urls_py":{"hash":"149d429a4ec140a5ece03884e79c762d","index":{"nums":[1,8,0,0,0,0,0],"html_filename":"books_urls_py.html","relative_filename":"books\\urls.py"}},"books_wsgi_py":{"hash":"57b960b369bc7990bd0786094370a99a","index":{"nums":[1,4,0,4,0,0,0],"html_filename":"books_wsgi_py.html","relative_filename":"books\\wsgi.py"}},"manage_py":{"hash":"4b39926856b73b3c24460bd34924620d","index":{"nums":[1,12,0,2,0,0,0],"html_filename":"manage_py.html","relative_filename":"manage.py"}},"store___init___py":{"hash":"af9d0d0de0ea3b71d198bc63f1499a7d","index":{"nums":[1,0,0,0,0,0,0],"html_filename":"store___init___py.html","relative_filename":"store\\__init__.py"}},"store_admin_py":{"hash":"c62099339459e900787aa82eee446290","index":{"nums":[1,3,0,0,0,0,0],"html_filename":"store_admin_py.html","relative_filename":"store\\admin.py"}},"store_apps_py":{"hash":"7375c7cad59cc6bc9ac2b3589be6b166","index":{"nums":[1,3,0,3,0,0,0],"html_filename":"store_apps_py.html","relative_filename":"store\\apps.py"}},"store_logic_py":{"hash":"960fc4b339c9d8db31c2071e8ec001b7","index":{"nums":[1,2,0,0,0,0,0],"html_filename":"store_logic_py.html","relative_filename":"store\\logic.py"}},"store_migrations_0001_initial_py":{"hash":"eed99cc1fdeaf41f33a04d07974834a0","index":{"nums":[1,5,0,0,0,0,0],"html_filename":"store_migrations_0001_initial_py.html","relative_filename":"store\\migrations\\0001_initial.py"}},"store_migrations___init___py":{"hash":"af9d0d0de0ea3b71d198bc63f1499a7d","index":{"nums":[1,0,0,0,0,0,0],"html_filename":"store_migrations___init___py.html","relative_filename":"store\\migrations\\__init__.py"}},"store_models_py":{"hash":"fac51db27fa6c377b992b05b3a77acf8","index":{"nums":[1,4,0,0,0,0,0],"html_filename":"store_models_py.html","relative_filename":"store\\models.py"}},"store_serializers_py":{"hash":"238da6c064ebcb15188f4326aeee2ad9","index":{"nums":[1,6,0,0,0,0,0],"html_filename":"store_serializers_py.html","relative_filename":"store\\serializers.py"}},"store_tests___init___py":{"hash":"af9d0d0de0ea3b71d198bc63f1499a7d","index":{"nums":[1,0,0,0,0,0,0],"html_filename":"store_tests___init___py.html","relative_filename":"store\\tests\\__init__.py"}},"store_tests_test_api_py":{"hash":"b50a5d0e759fe1ee8b88b5133d2a2c53","index":{"nums":[1,14,0,0,0,0,0],"html_filename":"store_tests_test_api_py.html","relative_filename":"store\\tests\\test_api.py"}},"store_tests_test_logic_py":{"hash":"413993f2940eed7a4bf7d9369e5e9a6d","index":{"nums":[1,12,0,2,0,0,0],"html_filename":"store_tests_test_logic_py.html","relative_filename":"store\\tests\\test_logic.py"}},"store_tests_test_serializers_py":{"hash":"5dcad6521edc6fa48b16013a01d9768a","index":{"nums":[1,10,0,0,0,0,0],"html_filename":"store_tests_test_serializers_py.html","relative_filename":"store\\tests\\test_serializers.py"}},"store_views_py":{"hash":"d6502105aeb7b9718626ed716c11bee7","index":{"nums":[1,7,0,0,0,0,0],"html_filename":"store_views_py.html","relative_filename":"store\\views.py"}}}}